{
  "id": "immunofluorescent_detection_of_collagen___1",
  "service": "[METHOD]: Collagen I Polyclonal Antibody",
  "issue_number": 142,
  "name_of_the_method_content": "immunofluorescent detection of collagen - 1",
  "method_description_content": "immunofluorescent detection of collagen - 1",
  "type_content": "_No response_",
  "relevant_vhp4safety_regulatory_question(s)_content": "_No response_",
  "vendor_content": "Thermofisher",
  "catalog_number_content": "PA5-90574",
  "catalog_webpage_content": "_No response_",
  "citation_content": "_No response_",
  "vhp4safety_workflow_stage_content": "AOP",
  "workflow_substage_content": "Increase fibrosis",
  "timestamp": "2025-09-05T12:51:38.207479Z"
}